{"title":"StreamNative Blog","url":"https://streamnative.io/blogs/","favicon":"data:,","elements":[{"contents":"<div data-v-3be64661=\"\" data-v-2803187e=\"\" class=\"md-card sn-card-root h-full overflow-hidden md-theme-default md-with-hover\" md-with-hover=\"\"><div data-v-2803187e=\"\" class=\"h-full hover:text-white\"><div data-v-2803187e=\"\" class=\"h-full md-ripple flex\"><div data-v-2803187e=\"\" class=\"hidden md:block w-80 flex-shrink-0\"><img data-v-2803187e=\"\" alt=\"How Proxima Beta Implemented CQRS and Event Sourcing on Top of Apache Pulsar and ScyllaDB\" src=\"/uploads/images/pulsar-and-scylladb.jpg\" class=\"h-full w-full w-full object-cover g-image\"></div><!----><div data-v-2803187e=\"\" class=\"flex-1 flex flex-col p-6  pl-10  \"><div data-v-2803187e=\"\" class=\"font-text mb-2 sn-text-16 sn-text-bold text-gray-dark\">\n            Proxima Beta, Apache Pulsar, ScyllaDB, CQRS, Event sourcing\n          </div><div data-v-2803187e=\"\" class=\"text-xl sn-text-25 sn-text-bold text-gray-darkest\">\n            How Proxima Beta Implemented CQRS and Event Sourcing on Top of Apache Pulsar and ScyllaDB\n          </div><p data-v-2803187e=\"\" class=\"max-h-18 overflow-ellipsis font-text line-clamp-3 sn-text-16 text-gray-dark\" style=\"margin-top: 20px;\">\n            \n          </p><div data-v-2803187e=\"\" class=\"font-text mt-2 mb-4 sn-text-16 text-gray\" style=\"margin-top: 20px;\">\n            November 15, 2022\n          </div><div data-v-2803187e=\"\" class=\"author-list\"><div data-v-2803187e=\"\" class=\"article-author mr-6\"><div data-v-2803187e=\"\" class=\"author-img\"><img data-v-2803187e=\"\" src=\"/uploads/images/lei-shi.jpg\" alt=\"head img\" class=\"img-thumbnail article-head-img\"></div><div data-v-2803187e=\"\" class=\"author-info\"><span data-v-2803187e=\"\">Lei Shi</span><div data-v-2803187e=\"\" class=\"author-share-box\"><!----><a data-v-2803187e=\"\" href=\"https://www.linkedin.com/in/lei-shi-b72a0033/\" target=\"_blank\"><img data-v-2803187e=\"\" src=\"/uploads/images/linkedin-icon.svg\" alt=\"linkedIn\" class=\"article-social opacity-50\"></a></div></div></div></div><div data-v-2803187e=\"\" class=\"font-bold ml-auto mt-auto sn-text-16 sn-text-bold\"><div data-v-2803187e=\"\" class=\"flex flex-row\"><span data-v-2803187e=\"\" class=\"hidden\">Learn More</span><i data-v-c35c051a=\"\" data-v-2803187e=\"\" class=\"md-icon md-icon-font text-current font-icon overflow-hidden md-theme-default text-black\">arrow_forward_ios</i></div></div></div> </div></div></div>","link":"https://streamnative.io/blog/case/2022-11-15-how-proxima-beta-implemented-cqrs-and-event-sourcing-on-top-of-apache-pulsar-and-scylladb/","retrieved":1668663620745},{"contents":"<div data-v-3be64661=\"\" data-v-2803187e=\"\" class=\"md-card sn-card-root h-full overflow-hidden md-theme-default md-with-hover\" md-with-hover=\"\"><div data-v-2803187e=\"\" class=\"h-full hover:text-white\"><div data-v-2803187e=\"\" class=\"h-full md-ripple flex\"><div data-v-2803187e=\"\" class=\"hidden md:block w-80 flex-shrink-0\"><img data-v-2803187e=\"\" alt=\"Announcing Conference Schedule for Pulsar Summit Asia 2022\" src=\"/uploads/images/pulsar-summit-asia-2022-schedule.jpg\" class=\"h-full w-full w-full object-cover g-image\"></div><!----><div data-v-2803187e=\"\" class=\"flex-1 flex flex-col p-6  pl-10  \"><div data-v-2803187e=\"\" class=\"font-text mb-2 sn-text-16 sn-text-bold text-gray-dark\">\n            Pulsar Summit Asia, Schedule\n          </div><div data-v-2803187e=\"\" class=\"text-xl sn-text-25 sn-text-bold text-gray-darkest\">\n            Announcing Conference Schedule for Pulsar Summit Asia 2022\n          </div><p data-v-2803187e=\"\" class=\"max-h-18 overflow-ellipsis font-text line-clamp-3 sn-text-16 text-gray-dark\" style=\"margin-top: 20px;\">\n            \n          </p><div data-v-2803187e=\"\" class=\"font-text mt-2 mb-4 sn-text-16 text-gray\" style=\"margin-top: 20px;\">\n            November 04, 2022\n          </div><div data-v-2803187e=\"\" class=\"author-list\"><div data-v-2803187e=\"\" class=\"article-author mr-6\"><div data-v-2803187e=\"\" class=\"author-img\"><img data-v-2803187e=\"\" src=\"/uploads/images/sherlock.png\" alt=\"head img\" class=\"img-thumbnail article-head-img\"></div><div data-v-2803187e=\"\" class=\"author-info\"><span data-v-2803187e=\"\">Sherlock Xu</span><div data-v-2803187e=\"\" class=\"author-share-box\"><!----><a data-v-2803187e=\"\" href=\"https://www.linkedin.com/in/sherlock-xu/\" target=\"_blank\"><img data-v-2803187e=\"\" src=\"/uploads/images/linkedin-icon.svg\" alt=\"linkedIn\" class=\"article-social opacity-50\"></a></div></div></div></div><div data-v-2803187e=\"\" class=\"font-bold ml-auto mt-auto sn-text-16 sn-text-bold\"><div data-v-2803187e=\"\" class=\"flex flex-row\"><span data-v-2803187e=\"\" class=\"hidden\">Learn More</span><i data-v-c35c051a=\"\" data-v-2803187e=\"\" class=\"md-icon md-icon-font text-current font-icon overflow-hidden md-theme-default text-black\">arrow_forward_ios</i></div></div></div> </div></div></div>","link":"https://streamnative.io/blog/community/2022-11-04-announcing-pulsar-summit-asia-2022-conference-schedule/","retrieved":1667540519403},{"contents":"<div data-v-3be64661=\"\" data-v-2803187e=\"\" class=\"md-card sn-card-root h-full overflow-hidden md-theme-default md-with-hover\" md-with-hover=\"\"><div data-v-2803187e=\"\" class=\"h-full hover:text-white\"><div data-v-2803187e=\"\" class=\"h-full md-ripple flex\"><div data-v-2803187e=\"\" class=\"hidden md:block w-80 flex-shrink-0\"><img data-v-2803187e=\"\" alt=\"Using Cloud Native Buildpacks to Improve the Function Image Building Capability of Function Mesh\" src=\"/uploads/images/buildpacks-function-mesh-cover.jpg\" class=\"h-full w-full w-full object-cover g-image\"></div><!----><div data-v-2803187e=\"\" class=\"flex-1 flex flex-col p-6  pl-10  \"><div data-v-2803187e=\"\" class=\"font-text mb-2 sn-text-16 sn-text-bold text-gray-dark\">\n            Apache Pulsar, Buildpack, Function, Function Mesh\n          </div><div data-v-2803187e=\"\" class=\"text-xl sn-text-25 sn-text-bold text-gray-darkest\">\n            Using Cloud Native Buildpacks to Improve the Function Image Building Capability of Function Mesh\n          </div><p data-v-2803187e=\"\" class=\"max-h-18 overflow-ellipsis font-text line-clamp-3 sn-text-16 text-gray-dark\" style=\"margin-top: 20px;\">\n            \n          </p><div data-v-2803187e=\"\" class=\"font-text mt-2 mb-4 sn-text-16 text-gray\" style=\"margin-top: 20px;\">\n            November 01, 2022\n          </div><div data-v-2803187e=\"\" class=\"author-list\"><div data-v-2803187e=\"\" class=\"article-author mr-6\"><div data-v-2803187e=\"\" class=\"author-img\"><img data-v-2803187e=\"\" src=\"/uploads/images/tian-fang.png\" alt=\"head img\" class=\"img-thumbnail article-head-img\"></div><div data-v-2803187e=\"\" class=\"author-info\"><span data-v-2803187e=\"\">Tian Fang</span><div data-v-2803187e=\"\" class=\"author-share-box\"><!----><a data-v-2803187e=\"\" href=\"\" target=\"_blank\" style=\"display: none;\"><img data-v-2803187e=\"\" src=\"/uploads/images/linkedin-icon.svg\" alt=\"linkedIn\" class=\"article-social opacity-50\"></a></div></div></div></div><div data-v-2803187e=\"\" class=\"font-bold ml-auto mt-auto sn-text-16 sn-text-bold\"><div data-v-2803187e=\"\" class=\"flex flex-row\"><span data-v-2803187e=\"\" class=\"hidden\">Learn More</span><i data-v-c35c051a=\"\" data-v-2803187e=\"\" class=\"md-icon md-icon-font text-current font-icon overflow-hidden md-theme-default text-black\">arrow_forward_ios</i></div></div></div> </div></div></div>","link":"https://streamnative.io/blog/engineering/2022-10-31-using-cloud-native-buildpacks-to-improve-the-function-image-building-capability-of-function-mesh/","retrieved":1667411654078},{"contents":"<div data-v-3be64661=\"\" data-v-2803187e=\"\" class=\"md-card sn-card-root h-full overflow-hidden md-theme-default md-with-hover\" md-with-hover=\"\"><div data-v-2803187e=\"\" class=\"h-full hover:text-white\"><div data-v-2803187e=\"\" class=\"h-full md-ripple flex\"><div data-v-2803187e=\"\" class=\"hidden md:block w-80 flex-shrink-0\"><img data-v-2803187e=\"\" alt=\"A Deep Dive into Transaction Buffer in Apache Pulsar\" src=\"/uploads/images/a-deep-dive-into-transaction-buffer-in-apache-pulsar.jpg\" class=\"h-full w-full w-full object-cover g-image\"></div><!----><div data-v-2803187e=\"\" class=\"flex-1 flex flex-col p-6  pl-10  \"><div data-v-2803187e=\"\" class=\"font-text mb-2 sn-text-16 sn-text-bold text-gray-dark\">\n            Apache Pulsar, Transactions, Transaction buffer\n          </div><div data-v-2803187e=\"\" class=\"text-xl sn-text-25 sn-text-bold text-gray-darkest\">\n            A Deep Dive into Transaction Buffer in Apache Pulsar\n          </div><p data-v-2803187e=\"\" class=\"max-h-18 overflow-ellipsis font-text line-clamp-3 sn-text-16 text-gray-dark\" style=\"margin-top: 20px;\">\n            \n          </p><div data-v-2803187e=\"\" class=\"font-text mt-2 mb-4 sn-text-16 text-gray\" style=\"margin-top: 20px;\">\n            October 24, 2022\n          </div><div data-v-2803187e=\"\" class=\"author-list\"><div data-v-2803187e=\"\" class=\"article-author mr-6\"><div data-v-2803187e=\"\" class=\"author-img\"><img data-v-2803187e=\"\" src=\"/uploads/images/xiangying.jpg\" alt=\"head img\" class=\"img-thumbnail article-head-img\"></div><div data-v-2803187e=\"\" class=\"author-info\"><span data-v-2803187e=\"\">Xiangying Meng</span><div data-v-2803187e=\"\" class=\"author-share-box\"><!----><a data-v-2803187e=\"\" href=\"https://www.linkedin.com/in/%E7%A5%A5%E8%BF%8E-%E5%AD%9F-b50813200/\" target=\"_blank\"><img data-v-2803187e=\"\" src=\"/uploads/images/linkedin-icon.svg\" alt=\"linkedIn\" class=\"article-social opacity-50\"></a></div></div></div></div><div data-v-2803187e=\"\" class=\"font-bold ml-auto mt-auto sn-text-16 sn-text-bold\"><div data-v-2803187e=\"\" class=\"flex flex-row\"><span data-v-2803187e=\"\" class=\"hidden\">Learn More</span><i data-v-c35c051a=\"\" data-v-2803187e=\"\" class=\"md-icon md-icon-font text-current font-icon overflow-hidden md-theme-default text-black\">arrow_forward_ios</i></div></div></div> </div></div></div>","link":"https://streamnative.io/blog/engineering/2022-10-24-a-deep-dive-into-transaction-buffer-in-apache-pulsar/","retrieved":1667411654078},{"contents":"<div data-v-3be64661=\"\" data-v-2803187e=\"\" class=\"md-card sn-card-root h-full overflow-hidden md-theme-default md-with-hover\" md-with-hover=\"\"><div data-v-2803187e=\"\" class=\"h-full hover:text-white\"><div data-v-2803187e=\"\" class=\"h-full md-ripple flex\"><div data-v-2803187e=\"\" class=\"hidden md:block w-80 flex-shrink-0\"><img data-v-2803187e=\"\" alt=\"600K Topics Per Cluster: Stability Optimization of Apache Pulsar at Tencent Cloud\" src=\"/uploads/images/apache-pulsar-at-tencent-cloud-cover.jpg\" class=\"h-full w-full w-full object-cover g-image\"></div><!----><div data-v-2803187e=\"\" class=\"flex-1 flex flex-col p-6  pl-10  \"><div data-v-2803187e=\"\" class=\"font-text mb-2 sn-text-16 sn-text-bold text-gray-dark\">\n            Apache Pulsar, Tencent Cloud, Stability Optimization\n          </div><div data-v-2803187e=\"\" class=\"text-xl sn-text-25 sn-text-bold text-gray-darkest\">\n            600K Topics Per Cluster: Stability Optimization of Apache Pulsar at Tencent Cloud\n          </div><p data-v-2803187e=\"\" class=\"max-h-18 overflow-ellipsis font-text line-clamp-3 sn-text-16 text-gray-dark\" style=\"margin-top: 20px;\">\n            \n          </p><div data-v-2803187e=\"\" class=\"font-text mt-2 mb-4 sn-text-16 text-gray\" style=\"margin-top: 20px;\">\n            October 20, 2022\n          </div><div data-v-2803187e=\"\" class=\"author-list\"><div data-v-2803187e=\"\" class=\"article-author mr-6\"><div data-v-2803187e=\"\" class=\"author-img\"><img data-v-2803187e=\"\" src=\"/uploads/images/avatar/rxl.png\" alt=\"head img\" class=\"img-thumbnail article-head-img\"></div><div data-v-2803187e=\"\" class=\"author-info\"><span data-v-2803187e=\"\">Xiaolong Ran</span><div data-v-2803187e=\"\" class=\"author-share-box\"><a data-v-2803187e=\"\" href=\"https://twitter.com/wolf4j1\" target=\"_blank\" class=\"left\"><img data-v-2803187e=\"\" src=\"/uploads/images/twitter-icon.svg\" alt=\"twitter\" class=\"article-social opacity-50\"></a><a data-v-2803187e=\"\" href=\"\" target=\"_blank\" style=\"display: none;\"><img data-v-2803187e=\"\" src=\"/uploads/images/linkedin-icon.svg\" alt=\"linkedIn\" class=\"article-social opacity-50\"></a></div></div></div></div><div data-v-2803187e=\"\" class=\"font-bold ml-auto mt-auto sn-text-16 sn-text-bold\"><div data-v-2803187e=\"\" class=\"flex flex-row\"><span data-v-2803187e=\"\" class=\"hidden\">Learn More</span><i data-v-c35c051a=\"\" data-v-2803187e=\"\" class=\"md-icon md-icon-font text-current font-icon overflow-hidden md-theme-default text-black\">arrow_forward_ios</i></div></div></div> </div></div></div>","link":"https://streamnative.io/blog/case/2022-10-20-600k-topics-per-cluster-stability-optimization-of-apache-pulsar-at-tencent-cloud/","retrieved":1667411654078},{"contents":"<div data-v-3be64661=\"\" data-v-2803187e=\"\" class=\"md-card sn-card-root h-full overflow-hidden md-theme-default md-with-hover\" md-with-hover=\"\"><div data-v-2803187e=\"\" class=\"h-full hover:text-white\"><div data-v-2803187e=\"\" class=\"h-full md-ripple flex\"><div data-v-2803187e=\"\" class=\"hidden md:block w-80 flex-shrink-0\"><img data-v-2803187e=\"\" alt=\"StreamNative’s Pulsar Operators Certified as Red Hat OpenShift Operators\" src=\"/uploads/images/cover-800x800.png\" class=\"h-full w-full w-full object-cover g-image\"></div><!----><div data-v-2803187e=\"\" class=\"flex-1 flex flex-col p-6  pl-10  \"><div data-v-2803187e=\"\" class=\"font-text mb-2 sn-text-16 sn-text-bold text-gray-dark\">\n            Red Hat, Openshift, Kubernetes, Pulsar Operators, StreamNative Platform\n          </div><div data-v-2803187e=\"\" class=\"text-xl sn-text-25 sn-text-bold text-gray-darkest\">\n            StreamNative’s Pulsar Operators Certified as Red Hat OpenShift Operators\n          </div><p data-v-2803187e=\"\" class=\"max-h-18 overflow-ellipsis font-text line-clamp-3 sn-text-16 text-gray-dark\" style=\"margin-top: 20px;\">\n            \n          </p><div data-v-2803187e=\"\" class=\"font-text mt-2 mb-4 sn-text-16 text-gray\" style=\"margin-top: 20px;\">\n            October 12, 2022\n          </div><div data-v-2803187e=\"\" class=\"author-list\"><div data-v-2803187e=\"\" class=\"article-author mr-6\"><div data-v-2803187e=\"\" class=\"author-img\"><img data-v-2803187e=\"\" src=\"/uploads/images/eric-shen.jpg\" alt=\"head img\" class=\"img-thumbnail article-head-img\"></div><div data-v-2803187e=\"\" class=\"author-info\"><span data-v-2803187e=\"\">Eric Shen</span><div data-v-2803187e=\"\" class=\"author-share-box\"><!----><a data-v-2803187e=\"\" href=\"\" target=\"_blank\" style=\"display: none;\"><img data-v-2803187e=\"\" src=\"/uploads/images/linkedin-icon.svg\" alt=\"linkedIn\" class=\"article-social opacity-50\"></a></div></div></div><div data-v-2803187e=\"\" class=\"article-author mr-6\"><div data-v-2803187e=\"\" class=\"author-img\"><img data-v-2803187e=\"\" src=\"/uploads/images/fushu.jpeg\" alt=\"head img\" class=\"img-thumbnail article-head-img\"></div><div data-v-2803187e=\"\" class=\"author-info\"><span data-v-2803187e=\"\">Fushu Wang</span><div data-v-2803187e=\"\" class=\"author-share-box\"><!----><a data-v-2803187e=\"\" href=\"\" target=\"_blank\" style=\"display: none;\"><img data-v-2803187e=\"\" src=\"/uploads/images/linkedin-icon.svg\" alt=\"linkedIn\" class=\"article-social opacity-50\"></a></div></div></div></div><div data-v-2803187e=\"\" class=\"font-bold ml-auto mt-auto sn-text-16 sn-text-bold\"><div data-v-2803187e=\"\" class=\"flex flex-row\"><span data-v-2803187e=\"\" class=\"hidden\">Learn More</span><i data-v-c35c051a=\"\" data-v-2803187e=\"\" class=\"md-icon md-icon-font text-current font-icon overflow-hidden md-theme-default text-black\">arrow_forward_ios</i></div></div></div> </div></div></div>","link":"https://streamnative.io/blog/release/2022-10-19-streamnatives-pulsar-operators-certified-as-red-hat-openshift-operators/","retrieved":1667411654078},{"contents":"<div data-v-3be64661=\"\" data-v-2803187e=\"\" class=\"md-card sn-card-root h-full overflow-hidden md-theme-default md-with-hover\" md-with-hover=\"\"><div data-v-2803187e=\"\" class=\"h-full hover:text-white\"><div data-v-2803187e=\"\" class=\"h-full md-ripple flex\"><div data-v-2803187e=\"\" class=\"hidden md:block w-80 flex-shrink-0\"><img data-v-2803187e=\"\" alt=\"How to Migrate from RabbitMQ to Apache Pulsar™\" src=\"/uploads/images/rabbit-to-pulsar.png\" class=\"h-full w-full w-full object-cover g-image\"></div><!----><div data-v-2803187e=\"\" class=\"flex-1 flex flex-col p-6  pl-10  \"><div data-v-2803187e=\"\" class=\"font-text mb-2 sn-text-16 sn-text-bold text-gray-dark\">\n            RabbitMQ, Cloud-native, Messaging, Message Queue\n          </div><div data-v-2803187e=\"\" class=\"text-xl sn-text-25 sn-text-bold text-gray-darkest\">\n            How to Migrate from RabbitMQ to Apache Pulsar™\n          </div><p data-v-2803187e=\"\" class=\"max-h-18 overflow-ellipsis font-text line-clamp-3 sn-text-16 text-gray-dark\" style=\"margin-top: 20px;\">\n            \n          </p><div data-v-2803187e=\"\" class=\"font-text mt-2 mb-4 sn-text-16 text-gray\" style=\"margin-top: 20px;\">\n            October 12, 2022\n          </div><div data-v-2803187e=\"\" class=\"author-list\"><div data-v-2803187e=\"\" class=\"article-author mr-6\"><div data-v-2803187e=\"\" class=\"author-img\"><img data-v-2803187e=\"\" src=\"/uploads/images/david-kjerrumgaard-profile-pic.jpg\" alt=\"head img\" class=\"img-thumbnail article-head-img\"></div><div data-v-2803187e=\"\" class=\"author-info\"><span data-v-2803187e=\"\">David Kjerrumgaard</span><div data-v-2803187e=\"\" class=\"author-share-box\"><!----><a data-v-2803187e=\"\" href=\"https://www.linkedin.com/in/davidkj/\" target=\"_blank\"><img data-v-2803187e=\"\" src=\"/uploads/images/linkedin-icon.svg\" alt=\"linkedIn\" class=\"article-social opacity-50\"></a></div></div></div></div><div data-v-2803187e=\"\" class=\"font-bold ml-auto mt-auto sn-text-16 sn-text-bold\"><div data-v-2803187e=\"\" class=\"flex flex-row\"><span data-v-2803187e=\"\" class=\"hidden\">Learn More</span><i data-v-c35c051a=\"\" data-v-2803187e=\"\" class=\"md-icon md-icon-font text-current font-icon overflow-hidden md-theme-default text-black\">arrow_forward_ios</i></div></div></div> </div></div></div>","link":"https://streamnative.io/blog/engineering/2022-10-12-how-to-migrate-from-rabbitmq-to-apache-pulsar/","retrieved":1667411654079},{"contents":"<div data-v-3be64661=\"\" data-v-2803187e=\"\" class=\"md-card sn-card-root h-full overflow-hidden md-theme-default md-with-hover\" md-with-hover=\"\"><div data-v-2803187e=\"\" class=\"h-full hover:text-white\"><div data-v-2803187e=\"\" class=\"h-full md-ripple flex\"><div data-v-2803187e=\"\" class=\"hidden md:block w-80 flex-shrink-0\"><img data-v-2803187e=\"\" alt=\"Improving Regular Expression-Based Subscriptions in Pulsar Consumers\" src=\"/uploads/images/improve-regex-sub-cover.jpg\" class=\"h-full w-full w-full object-cover g-image\"></div><!----><div data-v-2803187e=\"\" class=\"flex-1 flex flex-col p-6  pl-10  \"><div data-v-2803187e=\"\" class=\"font-text mb-2 sn-text-16 sn-text-bold text-gray-dark\">\n            Pulsar, Regex-based subscriptions\n          </div><div data-v-2803187e=\"\" class=\"text-xl sn-text-25 sn-text-bold text-gray-darkest\">\n            Improving Regular Expression-Based Subscriptions in Pulsar Consumers\n          </div><p data-v-2803187e=\"\" class=\"max-h-18 overflow-ellipsis font-text line-clamp-3 sn-text-16 text-gray-dark\" style=\"margin-top: 20px;\">\n            \n          </p><div data-v-2803187e=\"\" class=\"font-text mt-2 mb-4 sn-text-16 text-gray\" style=\"margin-top: 20px;\">\n            October 12, 2022\n          </div><div data-v-2803187e=\"\" class=\"author-list\"><div data-v-2803187e=\"\" class=\"article-author mr-6\"><div data-v-2803187e=\"\" class=\"author-img\"><img data-v-2803187e=\"\" src=\"/uploads/images/andras-beni.jpg\" alt=\"head img\" class=\"img-thumbnail article-head-img\"></div><div data-v-2803187e=\"\" class=\"author-info\"><span data-v-2803187e=\"\">Andras Beni</span><div data-v-2803187e=\"\" class=\"author-share-box\"><!----><a data-v-2803187e=\"\" href=\"https://www.linkedin.com/in/andr%C3%A1s-b%C3%A9ni/\" target=\"_blank\"><img data-v-2803187e=\"\" src=\"/uploads/images/linkedin-icon.svg\" alt=\"linkedIn\" class=\"article-social opacity-50\"></a></div></div></div></div><div data-v-2803187e=\"\" class=\"font-bold ml-auto mt-auto sn-text-16 sn-text-bold\"><div data-v-2803187e=\"\" class=\"flex flex-row\"><span data-v-2803187e=\"\" class=\"hidden\">Learn More</span><i data-v-c35c051a=\"\" data-v-2803187e=\"\" class=\"md-icon md-icon-font text-current font-icon overflow-hidden md-theme-default text-black\">arrow_forward_ios</i></div></div></div> </div></div></div>","link":"https://streamnative.io/blog/engineering/2022-10-12-improving-regular-expression-based-subscriptions-in-pulsar-consumers/","retrieved":1667411654081},{"contents":"<div data-v-3be64661=\"\" data-v-2803187e=\"\" class=\"md-card sn-card-root h-full overflow-hidden md-theme-default md-with-hover\" md-with-hover=\"\"><div data-v-2803187e=\"\" class=\"h-full hover:text-white\"><div data-v-2803187e=\"\" class=\"h-full md-ripple flex\"><div data-v-2803187e=\"\" class=\"hidden md:block w-80 flex-shrink-0\"><img data-v-2803187e=\"\" alt=\"Announcing the Flink-Pulsar SQL Connector\" src=\"/uploads/images/flink-sql-connector.png\" class=\"h-full w-full w-full object-cover g-image\"></div><!----><div data-v-2803187e=\"\" class=\"flex-1 flex flex-col p-6  pl-10  \"><div data-v-2803187e=\"\" class=\"font-text mb-2 sn-text-16 sn-text-bold text-gray-dark\">\n            Apache Flink, Pulsar Ecosystem, Flink SQL, Connector\n          </div><div data-v-2803187e=\"\" class=\"text-xl sn-text-25 sn-text-bold text-gray-darkest\">\n            Announcing the Flink-Pulsar SQL Connector\n          </div><p data-v-2803187e=\"\" class=\"max-h-18 overflow-ellipsis font-text line-clamp-3 sn-text-16 text-gray-dark\" style=\"margin-top: 20px;\">\n            \n          </p><div data-v-2803187e=\"\" class=\"font-text mt-2 mb-4 sn-text-16 text-gray\" style=\"margin-top: 20px;\">\n            September 29, 2022\n          </div><div data-v-2803187e=\"\" class=\"author-list\"><div data-v-2803187e=\"\" class=\"article-author mr-6\"><div data-v-2803187e=\"\" class=\"author-img\"><img data-v-2803187e=\"\" src=\"/uploads/images/screen-shot-2022-08-30-at-11.51.37-am.png\" alt=\"head img\" class=\"img-thumbnail article-head-img\"></div><div data-v-2803187e=\"\" class=\"author-info\"><span data-v-2803187e=\"\">Yufei Zhang</span><div data-v-2803187e=\"\" class=\"author-share-box\"><!----><a data-v-2803187e=\"\" href=\"\" target=\"_blank\" style=\"display: none;\"><img data-v-2803187e=\"\" src=\"/uploads/images/linkedin-icon.svg\" alt=\"linkedIn\" class=\"article-social opacity-50\"></a></div></div></div></div><div data-v-2803187e=\"\" class=\"font-bold ml-auto mt-auto sn-text-16 sn-text-bold\"><div data-v-2803187e=\"\" class=\"flex flex-row\"><span data-v-2803187e=\"\" class=\"hidden\">Learn More</span><i data-v-c35c051a=\"\" data-v-2803187e=\"\" class=\"md-icon md-icon-font text-current font-icon overflow-hidden md-theme-default text-black\">arrow_forward_ios</i></div></div></div> </div></div></div>","link":"https://streamnative.io/blog/release/2022-09-29-announcing-the-flink-pulsar-sql-connector/","retrieved":1667411654082},{"contents":"<div data-v-3be64661=\"\" data-v-2803187e=\"\" class=\"md-card sn-card-root h-full overflow-hidden md-theme-default md-with-hover\" md-with-hover=\"\"><div data-v-2803187e=\"\" class=\"h-full hover:text-white\"><div data-v-2803187e=\"\" class=\"h-full md-ripple flex\"><div data-v-2803187e=\"\" class=\"hidden md:block w-80 flex-shrink-0\"><img data-v-2803187e=\"\" alt=\"A Deep Dive into Transaction Coordinators in Apache Pulsar \" src=\"/uploads/images/transaction-coordinators-cover.jpg\" class=\"h-full w-full w-full object-cover g-image\"></div><!----><div data-v-2803187e=\"\" class=\"flex-1 flex flex-col p-6  pl-10  \"><div data-v-2803187e=\"\" class=\"font-text mb-2 sn-text-16 sn-text-bold text-gray-dark\">\n            Pulsar, Transactions, Transaction Coordinators\n          </div><div data-v-2803187e=\"\" class=\"text-xl sn-text-25 sn-text-bold text-gray-darkest\">\n            A Deep Dive into Transaction Coordinators in Apache Pulsar \n          </div><p data-v-2803187e=\"\" class=\"max-h-18 overflow-ellipsis font-text line-clamp-3 sn-text-16 text-gray-dark\" style=\"margin-top: 20px;\">\n            \n          </p><div data-v-2803187e=\"\" class=\"font-text mt-2 mb-4 sn-text-16 text-gray\" style=\"margin-top: 20px;\">\n            September 29, 2022\n          </div><div data-v-2803187e=\"\" class=\"author-list\"><div data-v-2803187e=\"\" class=\"article-author mr-6\"><div data-v-2803187e=\"\" class=\"author-img\"><img data-v-2803187e=\"\" src=\"/uploads/images/team/penghui.jpg\" alt=\"head img\" class=\"img-thumbnail article-head-img\"></div><div data-v-2803187e=\"\" class=\"author-info\"><span data-v-2803187e=\"\">Penghui Li</span><div data-v-2803187e=\"\" class=\"author-share-box\"><a data-v-2803187e=\"\" href=\"https://twitter.com/lipenghui6\" target=\"_blank\" class=\"left\"><img data-v-2803187e=\"\" src=\"/uploads/images/twitter-icon.svg\" alt=\"twitter\" class=\"article-social opacity-50\"></a><a data-v-2803187e=\"\" href=\"https://www.linkedin.com/in/penghui-li-244173184/\" target=\"_blank\"><img data-v-2803187e=\"\" src=\"/uploads/images/linkedin-icon.svg\" alt=\"linkedIn\" class=\"article-social opacity-50\"></a></div></div></div><div data-v-2803187e=\"\" class=\"article-author mr-6\"><div data-v-2803187e=\"\" class=\"author-img\"><img data-v-2803187e=\"\" src=\"/uploads/images/team/bocong.jpg\" alt=\"head img\" class=\"img-thumbnail article-head-img\"></div><div data-v-2803187e=\"\" class=\"author-info\"><span data-v-2803187e=\"\">Bo Cong</span><div data-v-2803187e=\"\" class=\"author-share-box\"><a data-v-2803187e=\"\" href=\"https://twitter.com/hXQwZLAwlZhMX8G\" target=\"_blank\" class=\"left\"><img data-v-2803187e=\"\" src=\"/uploads/images/twitter-icon.svg\" alt=\"twitter\" class=\"article-social opacity-50\"></a><a data-v-2803187e=\"\" href=\"\" target=\"_blank\" style=\"display: none;\"><img data-v-2803187e=\"\" src=\"/uploads/images/linkedin-icon.svg\" alt=\"linkedIn\" class=\"article-social opacity-50\"></a></div></div></div></div><div data-v-2803187e=\"\" class=\"font-bold ml-auto mt-auto sn-text-16 sn-text-bold\"><div data-v-2803187e=\"\" class=\"flex flex-row\"><span data-v-2803187e=\"\" class=\"hidden\">Learn More</span><i data-v-c35c051a=\"\" data-v-2803187e=\"\" class=\"md-icon md-icon-font text-current font-icon overflow-hidden md-theme-default text-black\">arrow_forward_ios</i></div></div></div> </div></div></div>","link":"https://streamnative.io/blog/engineering/2022-09-29-deep-dive-into-transaction-coordinators-in-apache-pulsar/","retrieved":1667411654083},{"contents":"<div data-v-3be64661=\"\" data-v-2803187e=\"\" class=\"md-card sn-card-root h-full overflow-hidden md-theme-default md-with-hover\" md-with-hover=\"\"><div data-v-2803187e=\"\" class=\"h-full hover:text-white\"><div data-v-2803187e=\"\" class=\"h-full md-ripple flex\"><div data-v-2803187e=\"\" class=\"hidden md:block w-80 flex-shrink-0\"><img data-v-2803187e=\"\" alt=\"A Deep Dive into the Topic Data Lifecycle in Apache Pulsar\" src=\"/uploads/images/a-deep-dive-into-the-topic-data-lifecycle-in-apache-pulsar-cover.jpg\" class=\"h-full w-full w-full object-cover g-image\"></div><!----><div data-v-2803187e=\"\" class=\"flex-1 flex flex-col p-6  pl-10  \"><div data-v-2803187e=\"\" class=\"font-text mb-2 sn-text-16 sn-text-bold text-gray-dark\">\n            Pulsar, Data Lifecycle, Retention, TTL\n          </div><div data-v-2803187e=\"\" class=\"text-xl sn-text-25 sn-text-bold text-gray-darkest\">\n            A Deep Dive into the Topic Data Lifecycle in Apache Pulsar\n          </div><p data-v-2803187e=\"\" class=\"max-h-18 overflow-ellipsis font-text line-clamp-3 sn-text-16 text-gray-dark\" style=\"margin-top: 20px;\">\n            \n          </p><div data-v-2803187e=\"\" class=\"font-text mt-2 mb-4 sn-text-16 text-gray\" style=\"margin-top: 20px;\">\n            September 27, 2022\n          </div><div data-v-2803187e=\"\" class=\"author-list\"><div data-v-2803187e=\"\" class=\"article-author mr-6\"><div data-v-2803187e=\"\" class=\"author-img\"><img data-v-2803187e=\"\" src=\"/uploads/images/picture2.png\" alt=\"head img\" class=\"img-thumbnail article-head-img\"></div><div data-v-2803187e=\"\" class=\"author-info\"><span data-v-2803187e=\"\">Hang Chen</span><div data-v-2803187e=\"\" class=\"author-share-box\"><!----><a data-v-2803187e=\"\" href=\"https://www.linkedin.com/in/hang-chen-135525201/\" target=\"_blank\"><img data-v-2803187e=\"\" src=\"/uploads/images/linkedin-icon.svg\" alt=\"linkedIn\" class=\"article-social opacity-50\"></a></div></div></div></div><div data-v-2803187e=\"\" class=\"font-bold ml-auto mt-auto sn-text-16 sn-text-bold\"><div data-v-2803187e=\"\" class=\"flex flex-row\"><span data-v-2803187e=\"\" class=\"hidden\">Learn More</span><i data-v-c35c051a=\"\" data-v-2803187e=\"\" class=\"md-icon md-icon-font text-current font-icon overflow-hidden md-theme-default text-black\">arrow_forward_ios</i></div></div></div> </div></div></div>","link":"https://streamnative.io/blog/engineering/2022-09-27-a-deep-dive-into-topic-data-lifecycle-in-apache-pulsar/","retrieved":1667411654084},{"contents":"<div data-v-3be64661=\"\" data-v-2803187e=\"\" class=\"md-card sn-card-root h-full overflow-hidden md-theme-default md-with-hover\" md-with-hover=\"\"><div data-v-2803187e=\"\" class=\"h-full hover:text-white\"><div data-v-2803187e=\"\" class=\"h-full md-ripple flex\"><div data-v-2803187e=\"\" class=\"hidden md:block w-80 flex-shrink-0\"><img data-v-2803187e=\"\" alt=\"The Beauty of Apache Pulsar: Individual Message Acknowledgment\" src=\"/uploads/images/individual-message-acknowledgment.jpg\" class=\"h-full w-full w-full object-cover g-image\"></div><!----><div data-v-2803187e=\"\" class=\"flex-1 flex flex-col p-6  pl-10  \"><div data-v-2803187e=\"\" class=\"font-text mb-2 sn-text-16 sn-text-bold text-gray-dark\">\n            Pulsar, Individual Message Acknowledgment\n          </div><div data-v-2803187e=\"\" class=\"text-xl sn-text-25 sn-text-bold text-gray-darkest\">\n            The Beauty of Apache Pulsar: Individual Message Acknowledgment\n          </div><p data-v-2803187e=\"\" class=\"max-h-18 overflow-ellipsis font-text line-clamp-3 sn-text-16 text-gray-dark\" style=\"margin-top: 20px;\">\n            \n          </p><div data-v-2803187e=\"\" class=\"font-text mt-2 mb-4 sn-text-16 text-gray\" style=\"margin-top: 20px;\">\n            September 22, 2022\n          </div><div data-v-2803187e=\"\" class=\"author-list\"><div data-v-2803187e=\"\" class=\"article-author mr-6\"><div data-v-2803187e=\"\" class=\"author-img\"><img data-v-2803187e=\"\" src=\"/uploads/images/asaf-mesika.jpg\" alt=\"head img\" class=\"img-thumbnail article-head-img\"></div><div data-v-2803187e=\"\" class=\"author-info\"><span data-v-2803187e=\"\">Asaf Mesika</span><div data-v-2803187e=\"\" class=\"author-share-box\"><!----><a data-v-2803187e=\"\" href=\"https://www.linkedin.com/in/asafmesika/\" target=\"_blank\"><img data-v-2803187e=\"\" src=\"/uploads/images/linkedin-icon.svg\" alt=\"linkedIn\" class=\"article-social opacity-50\"></a></div></div></div></div><div data-v-2803187e=\"\" class=\"font-bold ml-auto mt-auto sn-text-16 sn-text-bold\"><div data-v-2803187e=\"\" class=\"flex flex-row\"><span data-v-2803187e=\"\" class=\"hidden\">Learn More</span><i data-v-c35c051a=\"\" data-v-2803187e=\"\" class=\"md-icon md-icon-font text-current font-icon overflow-hidden md-theme-default text-black\">arrow_forward_ios</i></div></div></div> </div></div></div>","link":"https://streamnative.io/blog/engineering/2022-09-22-the-beauty-of-apache-pulsar-individual-message-acknowledgment/","retrieved":1667411654085}]}